pyds/__init__.py
pyds/version.py
pyds/cli/__init__.py
pyds/cli/analysis.py
pyds/cli/environment.py
pyds/cli/pixi.py
pyds/cli/project.py
pyds/cli/system.py
pyds/cli/talk.py
pyds/templates/analysis/cookiecutter.json
pyds/templates/analysis/{{ cookiecutter.__repo_name }}/.gitignore
pyds/templates/analysis/{{ cookiecutter.__repo_name }}/.pre-commit-config.yaml
pyds/templates/analysis/{{ cookiecutter.__repo_name }}/README.md
pyds/templates/analysis/{{ cookiecutter.__repo_name }}/pyproject.toml
pyds/templates/analysis/{{ cookiecutter.__repo_name }}/.github/copilot-instructions.md
pyds/templates/analysis/{{ cookiecutter.__repo_name }}/notebooks/example.ipynb
pyds/templates/project/cookiecutter.json
pyds/templates/project/{{ cookiecutter.__repo_name }}/.bumpversion.cfg
pyds/templates/project/{{ cookiecutter.__repo_name }}/.flake8
pyds/templates/project/{{ cookiecutter.__repo_name }}/.gitignore
pyds/templates/project/{{ cookiecutter.__repo_name }}/.pre-commit-config.yaml
pyds/templates/project/{{ cookiecutter.__repo_name }}/MANIFEST.in
pyds/templates/project/{{ cookiecutter.__repo_name }}/README.md
pyds/templates/project/{{ cookiecutter.__repo_name }}/mkdocs.yaml
pyds/templates/project/{{ cookiecutter.__repo_name }}/pyproject.toml
pyds/templates/project/{{ cookiecutter.__repo_name }}/.devcontainer/Dockerfile
pyds/templates/project/{{ cookiecutter.__repo_name }}/.devcontainer/devcontainer.json
pyds/templates/project/{{ cookiecutter.__repo_name }}/.github/copilot-instructions.md
pyds/templates/project/{{ cookiecutter.__repo_name }}/.github/dependabot.yml
pyds/templates/project/{{ cookiecutter.__repo_name }}/.github/workflows/code-style.yaml
pyds/templates/project/{{ cookiecutter.__repo_name }}/.github/workflows/docs.yaml
pyds/templates/project/{{ cookiecutter.__repo_name }}/.github/workflows/pr-tests.yaml
pyds/templates/project/{{ cookiecutter.__repo_name }}/.github/workflows/release-pypi-package.yaml
pyds/templates/project/{{ cookiecutter.__repo_name }}/docs/api.md
pyds_cli-0.6.12.dist-info/METADATA
pyds_cli-0.6.12.dist-info/WHEEL
pyds_cli-0.6.12.dist-info/entry_points.txt
pyds_cli-0.6.12.dist-info/top_level.txt
pyds_cli-0.6.12.dist-info/RECORD
