Metadata-Version: 2.4
Name: pyds-cli
Version: 0.6.12
Requires-Python: >=3.10
Requires-Dist: typer>=0.3.8
Requires-Dist: pyyaml>=6.0
Requires-Dist: jinja2>=3.0.2
Requires-Dist: loguru>=0.5.3
Requires-Dist: pyprojroot
Requires-Dist: python-dotenv>=0.19.1
Requires-Dist: rich>=10.12.0
Requires-Dist: ruamel.yaml>=0.17.17
Requires-Dist: case-converter>=1.0.2
Requires-Dist: jinja2-strcase>=0.0.2
Requires-Dist: cookiecutter
Requires-Dist: sh
Requires-Dist: pre-commit
Requires-Dist: juv>=0.2.18
Requires-Dist: tomli<3,>=2.0.2
